LICENSE
mixins/__init__.py
mixins/admin.py
mixins/fields.py
mixins/models.py
mixins/views.py
giant_mixins-0.3.8.dist-info/LICENSE
giant_mixins-0.3.8.dist-info/METADATA
giant_mixins-0.3.8.dist-info/WHEEL
giant_mixins-0.3.8.dist-info/RECORD
